signway_sdk/__init__.py
signway_sdk/sign_url.py
signway_sdk/signing_functions.py
signway_sdk/test_signed_url.py
signway_sdk-0.1.3.dist-info/LICENSE
signway_sdk-0.1.3.dist-info/METADATA
signway_sdk-0.1.3.dist-info/WHEEL
signway_sdk-0.1.3.dist-info/RECORD
